dsptoolbox/__init__.py
dsptoolbox/tools.py
dsptoolbox/audio_io/__init__.py
dsptoolbox/audio_io/audio_io.py
dsptoolbox/beamforming/__init__.py
dsptoolbox/beamforming/_beamforming.py
dsptoolbox/beamforming/beamforming.py
dsptoolbox/beamforming/enums.py
dsptoolbox/classes/__init__.py
dsptoolbox/classes/calibration_data.py
dsptoolbox/classes/exponential_average_filter.py
dsptoolbox/classes/filter.py
dsptoolbox/classes/filter_chain.py
dsptoolbox/classes/filter_helpers.py
dsptoolbox/classes/filterbank.py
dsptoolbox/classes/fir_filter_realtime.py
dsptoolbox/classes/group_delay_designer_phase_linearizer.py
dsptoolbox/classes/iir_filter_realtime.py
dsptoolbox/classes/impulse_response.py
dsptoolbox/classes/kautz_filter.py
dsptoolbox/classes/lattice_ladder_filter.py
dsptoolbox/classes/multibandsignal.py
dsptoolbox/classes/parallel_filter.py
dsptoolbox/classes/plots.py
dsptoolbox/classes/realtime_filter.py
dsptoolbox/classes/signal.py
dsptoolbox/classes/spectrum.py
dsptoolbox/classes/state_space_filter.py
dsptoolbox/classes/sv_filter.py
dsptoolbox/classes/warped_filters.py
dsptoolbox/distances/__init__.py
dsptoolbox/distances/_distances.py
dsptoolbox/distances/distances.py
dsptoolbox/effects/__init__.py
dsptoolbox/effects/_effects.py
dsptoolbox/effects/effects.py
dsptoolbox/effects/enums.py
dsptoolbox/filterbanks/__init__.py
dsptoolbox/filterbanks/_filterbank.py
dsptoolbox/filterbanks/filterbanks.py
dsptoolbox/generators/__init__.py
dsptoolbox/generators/_generators.py
dsptoolbox/generators/enums.py
dsptoolbox/generators/generators.py
dsptoolbox/helpers/__init__.py
dsptoolbox/helpers/ar_estimation.py
dsptoolbox/helpers/bytes_conversion.py
dsptoolbox/helpers/frequency_conversion.py
dsptoolbox/helpers/gain_and_level.py
dsptoolbox/helpers/latency.py
dsptoolbox/helpers/minimum_phase.py
dsptoolbox/helpers/other.py
dsptoolbox/helpers/polyphase.py
dsptoolbox/helpers/smoothing.py
dsptoolbox/helpers/spectrum_utilities.py
dsptoolbox/helpers/windows.py
dsptoolbox/plots/__init__.py
dsptoolbox-0.7.dist-info/METADATA
dsptoolbox-0.7.dist-info/WHEEL
dsptoolbox-0.7.dist-info/licenses/LICENSE
dsptoolbox-0.7.dist-info/RECORD
