Metadata-Version: 2.4
Name: dsptoolbox
Version: 0.7
Summary: Collection of dsp algorithms to be used for analysis of audio signals
Project-URL: Homepage, https://github.com/nico-franco-gomez/dsptoolbox
Project-URL: Bug Tracker, https://github.com/nico-franco-gomez/dsptoolbox/issues
Project-URL: Documentation, https://dsptoolbox.readthedocs.io/en/latest/
Author: Nicolas Franco-Gomez
License-Expression: MIT
License-File: LICENSE
Keywords: Digital Signal Processing,Prototyping,Research,dsp
Classifier: License :: OSI Approved :: MIT License
Classifier: Operating System :: OS Independent
Classifier: Programming Language :: Python :: 3
Classifier: Programming Language :: Python :: 3.11
Classifier: Programming Language :: Python :: 3.12
Classifier: Programming Language :: Python :: 3.13
Requires-Python: >=3.11
Requires-Dist: matplotlib~=3.10
Requires-Dist: numpy~=2.0; python_version <= '3.12'
Requires-Dist: numpy~=2.1; python_version >= '3.13'
Requires-Dist: scipy~=1.15
Requires-Dist: seaborn~=0.13
Requires-Dist: sounddevice~=0.5
Requires-Dist: soundfile~=0.13
Provides-Extra: use-numba
Requires-Dist: numba~=0.60; (python_version <= '3.12') and extra == 'use-numba'
Requires-Dist: numba~=0.61; (python_version ~= '3.13') and extra == 'use-numba'
